ezscore/__init__.py
ezscore/inference.py
ezscore/model_utils.py
ezscore-0.1.9.7.dist-info/licenses/LICENSE
ezscore-0.1.9.7.dist-info/METADATA
ezscore-0.1.9.7.dist-info/WHEEL
ezscore-0.1.9.7.dist-info/top_level.txt
ezscore-0.1.9.7.dist-info/RECORD
