Metadata-Version: 2.4
Name: ezscore
Version: 0.1.9.7
Summary: ezscore: Artifact-aware sleepr stage classifiers for forehead EEG
Author-email: "William G. Coon" <will.coon@jhuapl.edu>
Requires-Python: <3.12,>=3.9
License-File: LICENSE
Requires-Dist: tensorflow==2.15
Requires-Dist: keras_nlp==0.9.3
Requires-Dist: tf_keras
Requires-Dist: huggingface-hub>=0.33.1
Requires-Dist: mne
Requires-Dist: pandas
Requires-Dist: numpy
Requires-Dist: scikit-learn
Requires-Dist: matplotlib
Requires-Dist: seaborn
Requires-Dist: lspopt
Dynamic: license-file
